oasira/__init__.py
oasira/api_client.py
oasira/const.py
oasira-0.2.10.dist-info/METADATA
oasira-0.2.10.dist-info/WHEEL
oasira-0.2.10.dist-info/top_level.txt
oasira-0.2.10.dist-info/RECORD
