Metadata-Version: 2.1
Name: oasira
Version: 0.2.10
Summary: Python API client for Oasira with Firebase OAuth support, designed for Home Assistant integrations
Author-email: Development <dev@oasira.ai>
License: MIT
Project-URL: Homepage, https://github.com/effortlesshome
Project-URL: Repository, https://github.com/effortlesshome
Project-URL: Issues, https://github.com/effortlesshome
Keywords: oasira,home assistant,security,api,home automation
Classifier: Development Status :: 4 - Beta
Classifier: Intended Audience :: Developers
Classifier: License :: OSI Approved :: MIT License
Classifier: Programming Language :: Python :: 3
Classifier: Programming Language :: Python :: 3.9
Classifier: Programming Language :: Python :: 3.10
Classifier: Programming Language :: Python :: 3.11
Classifier: Programming Language :: Python :: 3.12
Classifier: Topic :: Home Automation
Classifier: Topic :: Software Development :: Libraries :: Python Modules
Requires-Python: >=3.9
Requires-Dist: aiohttp >=3.8.0
Provides-Extra: dev
Requires-Dist: black >=23.0.0 ; extra == 'dev'
Requires-Dist: isort >=5.12.0 ; extra == 'dev'
Requires-Dist: mypy >=1.0.0 ; extra == 'dev'
Requires-Dist: pylint >=2.17.0 ; extra == 'dev'
Requires-Dist: pytest-asyncio >=0.21.0 ; extra == 'dev'
Requires-Dist: pytest-cov >=4.0.0 ; extra == 'dev'
Requires-Dist: pytest >=7.0.0 ; extra == 'dev'
